multinterval/__init__.py
multinterval/interval.py
multinterval/multinterval.py
multinterval/types.py
multinterval-0.1.0.dist-info/METADATA
multinterval-0.1.0.dist-info/WHEEL
multinterval-0.1.0.dist-info/top_level.txt
multinterval-0.1.0.dist-info/RECORD
