Metadata-Version: 2.2
Name: multinterval
Version: 0.1.0
Summary: Represent large intervals of numeric/datetime data with a small memory footprint.
Author-email: Alex Koay <alexkoay88@gmail.com>
License: The MIT License (MIT)
Project-URL: Homepage, https://github.com/alexkoay/multinterval
Classifier: Development Status :: 4 - Beta
Classifier: Intended Audience :: Developers
Classifier: License :: OSI Approved :: MIT License
Classifier: Operating System :: OS Independent
Classifier: Programming Language :: Python :: 3
Classifier: Programming Language :: Python :: 3.10
Classifier: Programming Language :: Python :: 3.11
Classifier: Programming Language :: Python :: 3.13
Classifier: Programming Language :: Python :: 3 :: Only
Classifier: Topic :: Utilities
Requires-Python: >=3.10
